disopy/__init__.py
disopy/__main__.py
disopy/config.py
disopy/discord.py
disopy/env.py
disopy/logging.py
disopy/options.py
disopy/py.typed
disopy/cogs/base.py
disopy/cogs/misc.py
disopy/cogs/queue.py
disopy/cogs/search.py
disopy-2.2.3.dist-info/METADATA
disopy-2.2.3.dist-info/WHEEL
disopy-2.2.3.dist-info/entry_points.txt
disopy-2.2.3.dist-info/licenses/LICENSE.txt
disopy-2.2.3.dist-info/RECORD
