Metadata-Version: 2.3
Name: disopy
Version: 2.2.3
Summary: A Discord bot for listening music from a Subsonic server.
Project-URL: Repository, https://github.com/kutu-dev/disopy
Project-URL: Issues, https://github.com/kutu-dev/disopy/issues
Project-URL: Changelog, https://github.com/kutu-dev/disopy/blob/master/CHANGELOG.md
Author-email: "Jorge \"Kutu\" Dobón Blanco" <code@dobon.dev>
Keywords: bot,discord,music,opensubsonic,slash-commands,subsonic
Classifier: Development Status :: 5 - Production/Stable
Classifier: Environment :: Web Environment
Classifier: Intended Audience :: System Administrators
Classifier: License :: OSI Approved :: Mozilla Public License 2.0 (MPL 2.0)
Classifier: Operating System :: OS Independent
Classifier: Programming Language :: Python
Classifier: Programming Language :: Python :: 3
Classifier: Programming Language :: Python :: 3.13
Classifier: Topic :: Internet
Classifier: Topic :: Internet :: WWW/HTTP
Classifier: Topic :: Multimedia
Classifier: Typing :: Typed
Requires-Python: >=3.13.0
Requires-Dist: audioop-lts>=0.2.1
Requires-Dist: colorama>=0.4.6
Requires-Dist: discord-py[voice]>=2.4.0
Requires-Dist: knuckles>=1.2.0
Requires-Dist: platformdirs>=4.3.6
Requires-Dist: pynacl>=1.5.0
Requires-Dist: tomlkit>=0.12.0
